AviTwilTools/__init__.py
AviTwilTools/core.py
avitwiltools-1.0.5.dist-info/licenses/LICENSE
avitwiltools-1.0.5.dist-info/METADATA
avitwiltools-1.0.5.dist-info/WHEEL
avitwiltools-1.0.5.dist-info/top_level.txt
avitwiltools-1.0.5.dist-info/RECORD
