Metadata-Version: 2.4
Name: AviTwilTools
Version: 1.0.5
Summary: Unified Python package for folder and file management
Author-email: Avi Twil <avitwil@gmail.com>
License: MIT
Project-URL: Homepage, https://github.com/avitwil/AT_tools
Project-URL: Source, https://github.com/avitwil/AT_tools
Project-URL: Bug Tracker, https://github.com/avitwil/AT_tools/issues
Keywords: file,txt,json,csv,yaml,xml,dill,binary,database,VarDB,filesystem,folder,file,file management,folders,files
Classifier: Development Status :: 5 - Production/Stable
Classifier: Programming Language :: Python :: 3
Classifier: License :: OSI Approved :: MIT License
Classifier: Operating System :: OS Independent
Classifier: Topic :: Utilities
Requires-Python: >=3.10
License-File: LICENSE
Requires-Dist: dill>=0.3.6
Requires-Dist: PyYAML>=6.0
Requires-Dist: avi_tools>=1.0.8
Requires-Dist: lxml>=4.9.3
Dynamic: license-file
